mera2qasm/__init__.py
mera2qasm-0.1.dist-info/DESCRIPTION.rst
mera2qasm-0.1.dist-info/METADATA
mera2qasm-0.1.dist-info/RECORD
mera2qasm-0.1.dist-info/WHEEL
mera2qasm-0.1.dist-info/metadata.json
mera2qasm-0.1.dist-info/top_level.txt
