Metadata-Version: 2.0
Name: mera2qasm
Version: 0.1
Summary: Studies the noise resilience of mera circuit
Home-page: UNKNOWN
Author: Isaac Kim
Author-email: ikim@us.ibm.com
License: MIT
Platform: UNKNOWN
